reservation_calendar/__init__.py
reservation_calendar/reservation_calendar.py
reservation_calendar-1.0.dist-info/licenses/LICENSE
reservation_calendar-1.0.dist-info/METADATA
reservation_calendar-1.0.dist-info/WHEEL
reservation_calendar-1.0.dist-info/top_level.txt
reservation_calendar-1.0.dist-info/RECORD
