Metadata-Version: 2.4
Name: reservation_calendar
Version: 1.0
Summary: A Reservation Calendar System
Author-email: MrYutz <gregbazar@gmail.com>
Project-URL: Homepage, https://github.com/MrYutz/reservation_calendar
Classifier: Programming Language :: Python :: 3
Classifier: License :: OSI Approved :: MIT License
Classifier: Operating System :: OS Independent
Requires-Python: >=3.11
License-File: LICENSE
Provides-Extra: dev
Requires-Dist: pytest; extra == "dev"
Requires-Dist: pytest-cov; extra == "dev"
Dynamic: license-file
